Metadata-Version: 2.1
Name: passql
Version: 0.2.8
Summary: Super light ORM
Home-page: UNKNOWN
Author: Vladislav Mironov
Author-email: hidden120@mail.ru
License: UNKNOWN
Platform: UNKNOWN
Classifier: Programming Language :: Python :: 3.9
Classifier: License :: OSI Approved :: MIT License
Classifier: Operating System :: OS Independent
Requires-Python: >=3.6
